django_informixdb_dev/__init__.py
django_informixdb_dev/base.py
django_informixdb_dev/client.py
django_informixdb_dev/compiler.py
django_informixdb_dev/creation.py
django_informixdb_dev/datatypes.py
django_informixdb_dev/features.py
django_informixdb_dev/fields.py
django_informixdb_dev/introspection.py
django_informixdb_dev/operations.py
django_informixdb_dev/schema.py
django_informixdb_dev/tableignore.py
django_informixdb_dev/utils.py
django_informixdb_dev/version.py
django_informixdb_dev-0.1.dev0.dist-info/LICENSE
django_informixdb_dev-0.1.dev0.dist-info/METADATA
django_informixdb_dev-0.1.dev0.dist-info/WHEEL
django_informixdb_dev-0.1.dev0.dist-info/top_level.txt
django_informixdb_dev-0.1.dev0.dist-info/RECORD
