Metadata-Version: 2.1
Name: django_informixdb_dev
Version: 0.1.dev0
Summary: A database driver for Django to connect to an Informix db via ODBC
Author-email: Reecetech <opensource@reecetech.com.au>
License: APLv2
Project-URL: Homepage, https://github.com/reecetech/django_informixdb_dev
Project-URL: Repository, https://github.com/reecetech/django_informixdb_dev
Keywords: django,informix
Classifier: Development Status :: 4 - Beta
Classifier: Intended Audience :: Developers
Classifier: Topic :: Software Development
Classifier: Topic :: Scientific/Engineering
Classifier: License :: OSI Approved :: Apache Software License
Classifier: Programming Language :: Python :: 3
Classifier: Programming Language :: Python :: 3.7
Classifier: Programming Language :: Python :: 3.8
Classifier: Programming Language :: Python :: 3.9
Classifier: Programming Language :: Python :: 3.10
License-File: LICENSE
Requires-Dist: django<5,>=3.2.0
Requires-Dist: pyodbc<5,>=4.0.0
